signaturizer/__init__.py
signaturizer/exporter.py
signaturizer/signaturizer.py
tests/__init__.py
tests/helper.py
tests/test_exporter.py
tests/test_signaturizer.py
signaturizer-1.1.16.dist-info/LICENSE
signaturizer-1.1.16.dist-info/METADATA
signaturizer-1.1.16.dist-info/WHEEL
signaturizer-1.1.16.dist-info/top_level.txt
signaturizer-1.1.16.dist-info/RECORD
