Metadata-Version: 2.1
Name: signaturizer
Version: 1.1.16
Summary: Generate Chemical Checker signatures from molecules SMILES.
Home-page: http://gitlabsbnb.irbbarcelona.org/packages/signaturizer
Author: Martino Bertoni
Author-email: martino.bertoni@irbbarcelona.org
License: MIT License
Keywords: signaturizer bioactivity signatures chemicalchecker chemoinformatics
Classifier: License :: OSI Approved :: MIT License
Classifier: Programming Language :: Python :: 2
Classifier: Programming Language :: Python :: 3
Classifier: Programming Language :: Python :: 3.7
Classifier: Programming Language :: Python :: 3.8
Classifier: Programming Language :: Python :: 3.9
Classifier: Programming Language :: Python :: 3.10
License-File: LICENSE
Requires-Dist: tensorflow (==2.15.1)
Requires-Dist: tensorflow-hub (==0.16.1)
Requires-Dist: tqdm
